gtdicom/__init__.py
gtdicom/connection.py
gtdicom/exception.py
gtdicom/gtdicom.py
gtdicom/scu.py
gtdicom/utils.py
gtdicom/models/__init__.py
gtdicom/models/base.py
gtdicom/models/patient.py
gtdicom/models/series.py
gtdicom/models/study.py
gt_dicom_connector-0.0.2.dist-info/LICENSE
gt_dicom_connector-0.0.2.dist-info/METADATA
gt_dicom_connector-0.0.2.dist-info/WHEEL
gt_dicom_connector-0.0.2.dist-info/top_level.txt
gt_dicom_connector-0.0.2.dist-info/RECORD
