Metadata-Version: 2.1
Name: gt-dicom-connector
Version: 0.0.2
Summary: A DICOM Node Connector for Python
Home-page: https://github.com/gyrotools/gt-dicom-connector-py
Author: Martin Bührer
Author-email: info@gyrotools.com
License: UNKNOWN
Platform: UNKNOWN
Classifier: Programming Language :: Python :: 3
Classifier: License :: OSI Approved :: MIT License
Classifier: Operating System :: OS Independent
Requires-Python: >=3.6.0
Requires-Dist: pynetdicom
